coolprint/__init__.py
coolprint/coolprint.py
coolprint-0.0.2.dist-info/LICENSE.txt
coolprint-0.0.2.dist-info/METADATA
coolprint-0.0.2.dist-info/WHEEL
coolprint-0.0.2.dist-info/top_level.txt
coolprint-0.0.2.dist-info/RECORD
