Metadata-Version: 2.1
Name: coolprint
Version: 0.0.2
Summary: coolprint is a library that prints coolly.
Home-page: UNKNOWN
Author: bichanna
Author-email: nobu.bichanna@gmail.com
License: MIT
Keywords: python,cool,print,coolprint
Platform: UNKNOWN
Classifier: Programming Language :: Python :: 3
